datahygiene/__init__.py
datahygiene/__version__.py
datahygiene/cleaner.py
datahygiene_transformer-0.1.15.dist-info/licenses/LICENSE
datahygiene_transformer-0.1.15.dist-info/METADATA
datahygiene_transformer-0.1.15.dist-info/WHEEL
datahygiene_transformer-0.1.15.dist-info/top_level.txt
datahygiene_transformer-0.1.15.dist-info/RECORD
