Metadata-Version: 2.4
Name: datahygiene-transformer
Version: 0.1.15
Summary: A sklearn-compatible transformer for cleaning tabular data
Author-email: Your Name <you@example.com>
License-Expression: MIT
Classifier: Programming Language :: Python :: 3
Classifier: Operating System :: OS Independent
Requires-Python: >=3.7
License-File: LICENSE
Requires-Dist: pandas
Requires-Dist: numpy
Requires-Dist: scikit-learn
Requires-Dist: pyyaml
Dynamic: license-file
